common_module/NotionAPI.py
common_module/Task.py
common_module/TodoistAPI.py
common_module/User.py
common_module/__init__.py
common_sync_module/NotionAPI.py
common_sync_module/Task.py
common_sync_module/TodoistAPI.py
common_sync_module/User.py
common_sync_module/__init__.py
todoist_sync_gcp-0.1.2.dist-info/METADATA
todoist_sync_gcp-0.1.2.dist-info/WHEEL
todoist_sync_gcp-0.1.2.dist-info/top_level.txt
todoist_sync_gcp-0.1.2.dist-info/RECORD
