Metadata-Version: 2.1
Name: todoist-sync-gcp
Version: 0.1.2
Summary: UNKNOWN
Home-page: UNKNOWN
Author: UNKNOWN
Author-email: UNKNOWN
License: UNKNOWN
Platform: UNKNOWN
Requires-Dist: python-dateutil
Requires-Dist: google-cloud-bigquery
